{
  "port": 80,
  "baseURL": "",
  "address": "",
  "log": "stdout",
  "database": "/database/filebrowser.db",
  "root": "/srv",
  "auth": {
    "method": "json",
    "signup": false,
    "shell": ""
  },
  "branding": {
    "name": "Foundry Assets Manager",
    "disableExternal": true,
    "disableUsedPercentage": false
  },
  "server": {
    "root": "/srv",
    "baseURL": "",
    "socket": "",
    "tlsKey": "",
    "tlsCert": "",
    "enableThumbnails": true,
    "resizePreview": true,
    "enableExec": false,
    "typeDetectionByHeader": false
  },
  "commands": {
    "after_copy": [],
    "after_delete": [],
    "after_rename": [],
    "after_save": [],
    "after_upload": [],
    "before_copy": [],
    "before_delete": [],
    "before_rename": [],
    "before_save": [],
    "before_upload": []
  },
  "rules": []
}
